hdl/cache/darray.sv
module darray #(parameter block_size = 256) (input logic clk, rst, load,
                input logic [2:0] rd_addr, 
                input logic [2:0] wr_addr,
                input logic [block_size - 1:0] din, 
                output logic [block_size - 1:0] dout );

    logic [block_size - 1:0] data [5 : 0];
    logic [block_size - 1:0] out;

    always_ff @( posedge clk ) begin
        if (rst == 1'b1) begin
            for (int i = 0; i < 8; i = i + 1) data[i] <= 0;
        end
        
        else begin
            if (load) data[wr_addr] <= din;
        end
    end

    always_comb begin
        out = (load & (rd_addr == wr_addr)) ? din : data[rd_addr];
    end

    assign dout = out;

endmodule

hdl/cache/array.sv
module array #(
    parameter width = 1,
    parameter size_logn = 3
)(  input logic clk, rst, load,
    input logic [size_logn - 1:0] rd_addr, 
    input logic [size_logn - 1:0] wr_addr,
    input logic [width - 1:0] din, 
    output logic [width- 1:0] dout );

    localparam size = 2**size_logn;

    logic [width - 1 : 0] data [size - 1 : 0];
    logic [width - 1 : 0] out;

    always_ff @( posedge clk ) begin
        if (rst == 1'b1) begin
            for (int i = 0; i < size; i = i + 1) data[i] <= 0;
        end
        
        else begin
            if (load) data[wr_addr] <= din;
        end
    end

    always_comb begin
        out = data[rd_addr];
    end

    assign dout = out;

endmodule

hdl/cache/i_cache_datapath.sv
module i_cache_datapath(
    input logic clk, rst,

/* CPU <-> L1 I-Cache Interface */
    input logic [31:0] cache_addr,
    output logic [31:0] cache_rdata, // we're not writing data from CPU to I-cache (read only)

/* Cache <-> Main Memory/L2 Cache Interface */
    input logic [255:0] mmem_rdata,
    output logic [31:0] mmem_addr,
    output logic [31:0] mmem_wdata, // (LRU) we ARE writing data from L1 cache to L2/MM 

/* Control Signals */
    input logic ld_v,
    input logic ld_tag,
    input logic ld_data,
    output logic hit
);

    localparam nsets = 8;
    localparam nways = 2;
    localparam nways_log = $clog2(nways);

/* forgetting about spatial locality for now, purely temporal--we'll expand block sizes to 64/128/256 later*/
    logic load_tag [nways];
    logic load_v [nways];
    logic load_data [nways];
    logic hit_ [nways - 1 : 0];

    logic valid_out [nways - 1 : 0];
    logic [26:0] tag_out [nways - 1 : 0];
    logic [31:0] instr_out [nways - 1 : 0];

    logic [26:0] addr_tag;
    logic [2:0] block;
    logic [2:0] set;

    logic [nways_log - 1:0] ways_index;

   // mux8 mux (.d0(), .d1(), .d2(), .d3(), .d4(), .d5(), .d6(), .d7(), block, )

/* find_way(); finds the index of the way in which the tag matches. */
    function logic find_way();

        // in the event of a cache miss, this loop will not return
        for (logic [nways:0] i = 0; i < nways; ++i) begin
            if (valid_out[i] && (tag_out[i] == addr_tag)) begin
                return i;
            end
        end

        // loop for an invalid way
        for (logic [nways:0] i = 0; i < nways; ++i) begin
            if (valid_out[i] == 1'b0) begin
                return i;
            end
        end

        // do some plru implementation here ig

        // static return 0
        return 0;
    endfunction

    always_comb begin
        // set defaults
        addr_tag = cache_addr[31:8];
        set = cache_addr[7:5]; // 3 bits for the 8 total sets
        block = cache_addr[4:2]; // 3 bits for the block size of 8
        ways_index = 0;

        for (int i = 0; i < nways; i++) begin
            load_tag[i] = 1'b0;
            load_data[i] = 1'b0;
            load_v[i] = 1'b0;
        end

        // rest of the logic
        ways_index = find_way();

        load_v[ways_index] = ld_v;
        load_tag[ways_index] = ld_tag;
        load_data[ways_index] = ld_data;
        hit = valid_out[ways_index] && (tag_out[ways_index] == addr_tag);

        cache_rdata = instr_out[ways_index][32 * $unsigned(block) +: 32];
        mmem_wdata = instr_out[ways_index];
        mmem_addr = cache_addr; 

    end

    genvar i;
    generate
        for (i = 0; i < nways; ++i) begin
            array #(1, 3) valid ( .clk(clk), 
                                .rst(rst), 
                                .load(load_v[i]), 
                                .rd_addr(set), 
                                .wr_addr(set), 
                                .din(1'b1), 
                                .dout(valid_out[i]) );

            array #(3, 3) tag ( .clk(clk), 
                                        .rst(rst),  
                                        .load(load_tag[i]), 
                                        .rd_addr(set), 
                                        .wr_addr(set), 
                                        .din(addr_tag), 
                                        .dout(tag_out[i]) );

            darray instr ( .clk(clk), 
                                        .rst(rst), 
                                        .load(load_data[i]), 
                                        .rd_addr(set), 
                                        .wr_addr(set), 
                                        .din(mmem_rdata), 
                                        .dout(instr_out[i]) );
        end
    endgenerate
endmodule

hdl/cache/i_cache_control.sv
module i_cache_control (
    input logic clk,
/* CPU <-> Cache Controller */
    input logic cache_read,

/* Cache <-> Main Memory/L2 Cache Interface */
    input logic mmem_status,
    output logic mmem_r,

/* Control Signals */
    output logic ld_v,
    output logic ld_tag,
    output logic ld_data,
    input logic hit
);

    parameter IDLE = 2'b00, RMEM = 2'b01, WB = 2'b10;
    logic [1:0] state, next_state;


    // 3-state FSM for I-cache
    always_comb begin
        /* Default */
        ld_v = 1'b0;
        ld_tag = 1'b0;
        ld_data = 1'b0;

        case (state)
            IDLE : begin
                if (cache_read) begin
                    if (hit) begin
                        // update LRU
                    end

                    else mmem_r = 1'b1;
                end
            end

            RMEM : begin
                // buffer state to wait for memory read
                if (mmem_status) begin
                    ld_v = 1'b1;
                    ld_tag = 1'b1;
                    ld_data = 1'b1;
                end
            end

            WB : begin
                mmem_r = 1'b0;
            end
            
            default ;
        endcase
    end

    // next-state
    always_comb begin
        
        next_state = state;

        case (state)
            IDLE : begin
                if (cache_read) begin
                    if (~hit) next_state = RMEM;
                end
            end

            RMEM : begin
                if (mmem_status) next_state = WB;
            end

            WB : begin
                // unconditional transition into IDLE
                next_state = IDLE;
            end

            default next_state = IDLE;
        endcase
    end

    always_ff @( posedge clk ) begin
        state <= next_state;
    end

endmodule

hdl/cache/i_cache.sv

module i_cache(
    input logic clk, rst, cache_read, mmem_status,
    output logic mmem_r,
    input logic [31:0] cache_addr,
    input logic [255:0] mmem_rdata, 
    output logic [31:0] cache_resp, mmem_addr, mmem_wdata,
    output logic hit_
);

    logic ltag, ldata, ldv, hit;

    i_cache_control control (
    .clk(clk), .cache_read(cache_read), .mmem_status(mmem_status), 
    .ld_v(ldv), .ld_tag(ltag), .ld_data(ldata), .hit(hit), .mmem_r(mmem_r));

    i_cache_datapath dp (
    .clk(clk), .rst(rst), .cache_addr(cache_addr), .cache_rdata(cache_resp), 
    .mmem_rdata(mmem_rdata), .mmem_addr(mmem_addr), .mmem_wdata(mmem_wdata), 
    .ld_v(ldv), .ld_tag(ltag), .ld_data(ldata), .hit(hit));

    assign hit_ = hit;

endmodule

hvl/mem/mmemory.sv
module mmemory(input logic [31:0] a, input logic r,
            output logic [255:0] rd, output logic resp);
    logic [31:0] RAM [65535:0];

    initial begin
        $readmemh("../hvl/mem/rvtest.hex", RAM);
    end

    assign rd = (r == 1'b1) ? RAM[a[31:4]] : 255'bx;
    assign resp = r;
endmodule

hvl/icache_tb.sv
// our main memory for tb

`include "./mem/mmemory.sv"
`include "../hdl/cache/i_cache.sv"

module tb_();
reg clk;
reg rst_n;

localparam CLK_PERIOD = 10;
always #(CLK_PERIOD/2) clk=~clk;

logic cache_read;
logic mmem_status, mmem_r, hit;
logic v, tag, data;
logic [31:0] addr;
logic [255:0] mmem_out;
logic [31:0] cache_out;

logic [31:0] mmem_addr, mmem_wdata;

mmemory mem (addr, mmem_r, mmem_out, mmem_status);
i_cache cache (clk, rst_n, cache_read, mmem_status, mmem_r, addr,
    mmem_out, cache_out, mmem_addr, mmem_wdata, hit);

initial begin
    $dumpfile("icache.vcd");
    $dumpvars;

    rst_n = 1;
    #22;
    rst_n = 0;

    @(posedge clk);

    // simulate a cache miss 
    addr = 32'h00000001;
    cache_read = 1'b1;

    @(posedge clk);
    @(posedge clk);

    // should be a cache hit now
    addr = 32'h000000FF;
    cache_read = 1'b1;

    @(posedge clk);
    @(posedge clk);

    $finish;
end

endmodule

build/icache.vcd
$version Generated by VerilatedVcd $end
$timescale 1ps $end
 $scope module $rootio $end
 $upscope $end
 $scope module tb_ $end
  $var wire 1 #" clk $end
  $var wire 1 $" rst_n $end
  $var wire 32 /" CLK_PERIOD [31:0] $end
  $var wire 1 %" cache_read $end
  $var wire 1 3 mmem_status $end
  $var wire 1 3 mmem_r $end
  $var wire 1 ? hit $end
  $var wire 1 0" v $end
  $var wire 1 1" tag $end
  $var wire 1 2" data $end
  $var wire 32 &" addr [31:0] $end
  $var wire 256 4 mmem_out [255:0] $end
  $var wire 32 @ cache_out [31:0] $end
  $var wire 32 A mmem_addr [31:0] $end
  $var wire 32 B mmem_wdata [31:0] $end
  $scope module cache $end
   $var wire 1 #" clk $end
   $var wire 1 $" rst $end
   $var wire 1 %" cache_read $end
   $var wire 1 3 mmem_status $end
   $var wire 1 3 mmem_r $end
   $var wire 32 &" cache_addr [31:0] $end
   $var wire 256 4 mmem_rdata [255:0] $end
   $var wire 32 @ cache_resp [31:0] $end
   $var wire 32 A mmem_addr [31:0] $end
   $var wire 32 B mmem_wdata [31:0] $end
   $var wire 1 ? hit_ $end
   $var wire 1 < ltag $end
   $var wire 1 = ldata $end
   $var wire 1 > ldv $end
   $var wire 1 ? hit $end
   $scope module control $end
    $var wire 1 #" clk $end
    $var wire 1 %" cache_read $end
    $var wire 1 3 mmem_status $end
    $var wire 1 3 mmem_r $end
    $var wire 1 > ld_v $end
    $var wire 1 < ld_tag $end
    $var wire 1 = ld_data $end
    $var wire 1 ? hit $end
    $var wire 2 3" IDLE [1:0] $end
    $var wire 2 4" RMEM [1:0] $end
    $var wire 2 5" WB [1:0] $end
    $var wire 2 X state [1:0] $end
    $var wire 2 C next_state [1:0] $end
   $upscope $end
   $scope module dp $end
    $var wire 1 #" clk $end
    $var wire 1 $" rst $end
    $var wire 32 &" cache_addr [31:0] $end
    $var wire 32 @ cache_rdata [31:0] $end
    $var wire 256 4 mmem_rdata [255:0] $end
    $var wire 32 A mmem_addr [31:0] $end
    $var wire 32 B mmem_wdata [31:0] $end
    $var wire 1 > ld_v $end
    $var wire 1 < ld_tag $end
    $var wire 1 = ld_data $end
    $var wire 1 ? hit $end
    $var wire 32 6" nsets [31:0] $end
    $var wire 32 7" nways [31:0] $end
    $var wire 32 8" nways_log [31:0] $end
    $var wire 1 D load_tag[0] $end
    $var wire 1 E load_tag[1] $end
    $var wire 1 F load_v[0] $end
    $var wire 1 G load_v[1] $end
    $var wire 1 H load_data[0] $end
    $var wire 1 I load_data[1] $end
    $var wire 1 9" hit_[0] $end
    $var wire 1 :" hit_[1] $end
    $var wire 1 '" valid_out[0] $end
    $var wire 1 (" valid_out[1] $end
    $var wire 27 )" tag_out[0] [26:0] $end
    $var wire 27 *" tag_out[1] [26:0] $end
    $var wire 32 J instr_out[0] [31:0] $end
    $var wire 32 K instr_out[1] [31:0] $end
    $var wire 27 L addr_tag [26:0] $end
    $var wire 3 M block [2:0] $end
    $var wire 3 N set [2:0] $end
    $var wire 1 O ways_index [0:0] $end
    $scope module genblk1[0] $end
     $scope module instr $end
      $var wire 32 ;" block_size [31:0] $end
      $var wire 1 #" clk $end
      $var wire 1 $" rst $end
      $var wire 1 P load $end
      $var wire 3 N rd_addr [2:0] $end
      $var wire 3 N wr_addr [2:0] $end
      $var wire 256 4 din [255:0] $end
      $var wire 256 # dout [255:0] $end
      $var wire 256 Y data[0] [255:0] $end
      $var wire 256 a data[1] [255:0] $end
      $var wire 256 i data[2] [255:0] $end
      $var wire 256 q data[3] [255:0] $end
      $var wire 256 y data[4] [255:0] $end
      $var wire 256 #! data[5] [255:0] $end
      $var wire 256 # out [255:0] $end
      $scope module unnamedblk1 $end
       $var wire 32 +! i [31:0] $end
      $upscope $end
     $upscope $end
     $scope module tag $end
      $var wire 32 <" width [31:0] $end
      $var wire 32 <" size_logn [31:0] $end
      $var wire 1 #" clk $end
      $var wire 1 $" rst $end
      $var wire 1 Q load $end
      $var wire 3 N rd_addr [2:0] $end
      $var wire 3 N wr_addr [2:0] $end
      $var wire 3 R din [2:0] $end
      $var wire 3 +" dout [2:0] $end
      $var wire 32 6" size [31:0] $end
      $var wire 3 ,! data[0] [2:0] $end
      $var wire 3 -! data[1] [2:0] $end
      $var wire 3 .! data[2] [2:0] $end
      $var wire 3 /! data[3] [2:0] $end
      $var wire 3 0! data[4] [2:0] $end
      $var wire 3 1! data[5] [2:0] $end
      $var wire 3 2! data[6] [2:0] $end
      $var wire 3 3! data[7] [2:0] $end
      $var wire 3 +" out [2:0] $end
      $scope module unnamedblk1 $end
       $var wire 32 4! i [31:0] $end
      $upscope $end
     $upscope $end
     $scope module valid $end
      $var wire 32 8" width [31:0] $end
      $var wire 32 <" size_logn [31:0] $end
      $var wire 1 #" clk $end
      $var wire 1 $" rst $end
      $var wire 1 S load $end
      $var wire 3 N rd_addr [2:0] $end
      $var wire 3 N wr_addr [2:0] $end
      $var wire 1 =" din [0:0] $end
      $var wire 1 ," dout [0:0] $end
      $var wire 32 6" size [31:0] $end
      $var wire 1 5! data[0] [0:0] $end
      $var wire 1 6! data[1] [0:0] $end
      $var wire 1 7! data[2] [0:0] $end
      $var wire 1 8! data[3] [0:0] $end
      $var wire 1 9! data[4] [0:0] $end
      $var wire 1 :! data[5] [0:0] $end
      $var wire 1 ;! data[6] [0:0] $end
      $var wire 1 <! data[7] [0:0] $end
      $var wire 1 ," out [0:0] $end
      $scope module unnamedblk1 $end
       $var wire 32 =! i [31:0] $end
      $upscope $end
     $upscope $end
    $upscope $end
    $scope module genblk1[1] $end
     $scope module instr $end
      $var wire 32 ;" block_size [31:0] $end
      $var wire 1 #" clk $end
      $var wire 1 $" rst $end
      $var wire 1 T load $end
      $var wire 3 N rd_addr [2:0] $end
      $var wire 3 N wr_addr [2:0] $end
      $var wire 256 4 din [255:0] $end
      $var wire 256 + dout [255:0] $end
      $var wire 256 >! data[0] [255:0] $end
      $var wire 256 F! data[1] [255:0] $end
      $var wire 256 N! data[2] [255:0] $end
      $var wire 256 V! data[3] [255:0] $end
      $var wire 256 ^! data[4] [255:0] $end
      $var wire 256 f! data[5] [255:0] $end
      $var wire 256 + out [255:0] $end
      $scope module unnamedblk1 $end
       $var wire 32 n! i [31:0] $end
      $upscope $end
     $upscope $end
     $scope module tag $end
      $var wire 32 <" width [31:0] $end
      $var wire 32 <" size_logn [31:0] $end
      $var wire 1 #" clk $end
      $var wire 1 $" rst $end
      $var wire 1 U load $end
      $var wire 3 N rd_addr [2:0] $end
      $var wire 3 N wr_addr [2:0] $end
      $var wire 3 R din [2:0] $end
      $var wire 3 -" dout [2:0] $end
      $var wire 32 6" size [31:0] $end
      $var wire 3 o! data[0] [2:0] $end
      $var wire 3 p! data[1] [2:0] $end
      $var wire 3 q! data[2] [2:0] $end
      $var wire 3 r! data[3] [2:0] $end
      $var wire 3 s! data[4] [2:0] $end
      $var wire 3 t! data[5] [2:0] $end
      $var wire 3 u! data[6] [2:0] $end
      $var wire 3 v! data[7] [2:0] $end
      $var wire 3 -" out [2:0] $end
      $scope module unnamedblk1 $end
       $var wire 32 w! i [31:0] $end
      $upscope $end
     $upscope $end
     $scope module valid $end
      $var wire 32 8" width [31:0] $end
      $var wire 32 <" size_logn [31:0] $end
      $var wire 1 #" clk $end
      $var wire 1 $" rst $end
      $var wire 1 V load $end
      $var wire 3 N rd_addr [2:0] $end
      $var wire 3 N wr_addr [2:0] $end
      $var wire 1 =" din [0:0] $end
      $var wire 1 ." dout [0:0] $end
      $var wire 32 6" size [31:0] $end
      $var wire 1 x! data[0] [0:0] $end
      $var wire 1 y! data[1] [0:0] $end
      $var wire 1 z! data[2] [0:0] $end
      $var wire 1 {! data[3] [0:0] $end
      $var wire 1 |! data[4] [0:0] $end
      $var wire 1 }! data[5] [0:0] $end
      $var wire 1 ~! data[6] [0:0] $end
      $var wire 1 !" data[7] [0:0] $end
      $var wire 1 ." out [0:0] $end
      $scope module unnamedblk1 $end
       $var wire 32 "" i [31:0] $end
      $upscope $end
     $upscope $end
    $upscope $end
    $scope module unnamedblk3 $end
     $var wire 32 W i [31:0] $end
    $upscope $end
   $upscope $end
  $upscope $end
  $scope module mem $end
   $var wire 32 &" a [31:0] $end
   $var wire 1 3 r $end
   $var wire 256 4 rd [255:0] $end
   $var wire 1 3 resp $end
  $upscope $end
 $upscope $end
$enddefinitions $end


#0
b0000000000000000000000000000000000000000000000000000000000000000000000000000000000000000000000000000000000000000000000000000000000000000000000000000000000000000000000000000000000000000000000000000000000000000000000000000000000000000000000000000000000000000 #
b0000000000000000000000000000000000000000000000000000000000000000000000000000000000000000000000000000000000000000000000000000000000000000000000000000000000000000000000000000000000000000000000000000000000000000000000000000000000000000000000000000000000000000 +
03
b0000000000000000000000000000000000000000000000000000000000000000000000000000000000000000000000000000000000000000000000000000000000000000000000000000000000000000000000000000000000000000000000000000000000000000000000000000000000000000000000000000000000000000 4
0<
0=
0>
0?
b00000000000000000000000000000000 @
b00000000000000000000000000000000 A
b00000000000000000000000000000000 B
b00 C
0D
0E
0F
0G
0H
0I
b00000000000000000000000000000000 J
b00000000000000000000000000000000 K
b000000000000000000000000000 L
b000 M
b000 N
0O
0P
0Q
b000 R
0S
0T
0U
0V
b00000000000000000000000000000010 W
b00 X
b0000000000000000000000000000000000000000000000000000000000000000000000000000000000000000000000000000000000000000000000000000000000000000000000000000000000000000000000000000000000000000000000000000000000000000000000000000000000000000000000000000000000000000 Y
b0000000000000000000000000000000000000000000000000000000000000000000000000000000000000000000000000000000000000000000000000000000000000000000000000000000000000000000000000000000000000000000000000000000000000000000000000000000000000000000000000000000000000000 a
b0000000000000000000000000000000000000000000000000000000000000000000000000000000000000000000000000000000000000000000000000000000000000000000000000000000000000000000000000000000000000000000000000000000000000000000000000000000000000000000000000000000000000000 i
b0000000000000000000000000000000000000000000000000000000000000000000000000000000000000000000000000000000000000000000000000000000000000000000000000000000000000000000000000000000000000000000000000000000000000000000000000000000000000000000000000000000000000000 q
b0000000000000000000000000000000000000000000000000000000000000000000000000000000000000000000000000000000000000000000000000000000000000000000000000000000000000000000000000000000000000000000000000000000000000000000000000000000000000000000000000000000000000000 y
b0000000000000000000000000000000000000000000000000000000000000000000000000000000000000000000000000000000000000000000000000000000000000000000000000000000000000000000000000000000000000000000000000000000000000000000000000000000000000000000000000000000000000000 #!
b00000000000000000000000000000000 +!
b000 ,!
b000 -!
b000 .!
b000 /!
b000 0!
b000 1!
b000 2!
b000 3!
b00000000000000000000000000000000 4!
05!
06!
07!
08!
09!
0:!
0;!
0<!
b00000000000000000000000000000000 =!
b0000000000000000000000000000000000000000000000000000000000000000000000000000000000000000000000000000000000000000000000000000000000000000000000000000000000000000000000000000000000000000000000000000000000000000000000000000000000000000000000000000000000000000 >!
b0000000000000000000000000000000000000000000000000000000000000000000000000000000000000000000000000000000000000000000000000000000000000000000000000000000000000000000000000000000000000000000000000000000000000000000000000000000000000000000000000000000000000000 F!
b0000000000000000000000000000000000000000000000000000000000000000000000000000000000000000000000000000000000000000000000000000000000000000000000000000000000000000000000000000000000000000000000000000000000000000000000000000000000000000000000000000000000000000 N!
b0000000000000000000000000000000000000000000000000000000000000000000000000000000000000000000000000000000000000000000000000000000000000000000000000000000000000000000000000000000000000000000000000000000000000000000000000000000000000000000000000000000000000000 V!
b0000000000000000000000000000000000000000000000000000000000000000000000000000000000000000000000000000000000000000000000000000000000000000000000000000000000000000000000000000000000000000000000000000000000000000000000000000000000000000000000000000000000000000 ^!
b0000000000000000000000000000000000000000000000000000000000000000000000000000000000000000000000000000000000000000000000000000000000000000000000000000000000000000000000000000000000000000000000000000000000000000000000000000000000000000000000000000000000000000 f!
b00000000000000000000000000000000 n!
b000 o!
b000 p!
b000 q!
b000 r!
b000 s!
b000 t!
b000 u!
b000 v!
b00000000000000000000000000000000 w!
0x!
0y!
0z!
0{!
0|!
0}!
0~!
0!"
b00000000000000000000000000000000 ""
0#"
1$"
0%"
b00000000000000000000000000000000 &"
0'"
0("
b000000000000000000000000000 )"
b000000000000000000000000000 *"
b000 +"
0,"
b000 -"
0."
b00000000000000000000000000001010 /"
00"
01"
02"
b00 3"
b01 4"
b10 5"
b00000000000000000000000000001000 6"
b00000000000000000000000000000010 7"
b00000000000000000000000000000001 8"
09"
0:"
b00000000000000000000000100000000 ;"
b00000000000000000000000000000011 <"
1="
#5
b00000000000000000000000000001000 +!
b00000000000000000000000000001000 4!
b00000000000000000000000000001000 =!
b00000000000000000000000000001000 n!
b00000000000000000000000000001000 w!
b00000000000000000000000000001000 ""
1#"
#10
0#"
#15
1#"
#20
0#"
#22
0$"
#25
b0000000000000000000000000000000000000000000000000000000000000000000000000000000000000000000000000000000000000000000000000000000000000000000000000000000000000000000000000000000000000000000000000000000000000000000000000000000000000000010100000000000100010011 #
13
b0000000000000000000000000000000000000000000000000000000000000000000000000000000000000000000000000000000000000000000000000000000000000000000000000000000000000000000000000000000000000000000000000000000000000000000000000000000000000000010100000000000100010011 4
1<
1=
1>
b00000000010100000000000100010011 @
b00000000000000000000000000000001 A
b00000000010100000000000100010011 B
b10 C
1D
1F
1H
b00000000010100000000000100010011 J
1P
1Q
1S
b01 X
1#"
1%"
b00000000000000000000000000000001 &"
#30
0#"
#35
03
b0000000000000000000000000000000000000000000000000000000000000000000000000000000000000000000000000000000000000000000000000000000000000000000000000000000000000000000000000000000000000000000000000000000000000000000000000000000000000000000000000000000000000000 4
0<
0=
0>
1?
b00 C
0D
0F
0H
0P
0Q
0S
b10 X
b0000000000000000000000000000000000000000000000000000000000000000000000000000000000000000000000000000000000000000000000000000000000000000000000000000000000000000000000000000000000000000000000000000000000000000000000000000000000000000010100000000000100010011 Y
15!
1#"
1'"
1,"
#40
0#"
#45
b0000000000000000000000000000000000000000000000000000000000000000000000000000000000000000000000000000000000000000000000000000000000000000000000000000000000000000000000000000000000000000000000000000000000000000000000000000000000000000000000000000000000000000 #
13
b0000000000000000000000000000000000000000000000000000000000000000000000000000000000000000000000000000000000000000000000000000000000000000000000000000000000000000000000000000000000000000000000000000000000000000000000000000000000000000010100010000010010110011 4
0?
b00000000000000000000000000000000 @
b00000000000000000000000011111111 A
b00000000000000000000000000000000 B
b01 C
b00000000000000000000000000000000 J
b111 M
b111 N
b00 X
1#"
b00000000000000000000000011111111 &"
0'"
0,"
#50
0#"
#55
b0000000000000000000000000000000000000000000000000000000000000000000000000000000000000000000000000000000000000000000000000000000000000000000000000000000000000000000000000000000000000000000000000000000000000000000000000000000000000000010100010000010010110011 #
1<
1=
1>
b00000000010100010000010010110011 @
b00000000010100010000010010110011 B
b10 C
1D
1F
1H
b00000000010100010000010010110011 J
1P
1Q
1S
b01 X
1#"
#60
0#"
#65
b0000000000000000000000000000000000000000000000000000000000000000000000000000000000000000000000000000000000000000000000000000000000000000000000000000000000000000000000000000000000000000000000000000000000000000000000000000000000000000000000000000000000000000 #
03
b0000000000000000000000000000000000000000000000000000000000000000000000000000000000000000000000000000000000000000000000000000000000000000000000000000000000000000000000000000000000000000000000000000000000000000000000000000000000000000000000000000000000000000 4
0<
0=
0>
1?
b00000000000000000000000000000000 @
b00000000000000000000000000000000 B
b00 C
0D
0F
0H
b00000000000000000000000000000000 J
0P
0Q
0S
b10 X
1<!
1#"
1'"
1,"
